{"status":"succeeded","createdDateTime":"2025-04-03T07:32:29Z","lastUpdatedDateTime":"2025-04-03T07:32:29Z","analyzeResult":{"apiVersion":"2099-01-01-preview","modelId":"prebuilt-invoice","stringIndexType":"utf16CodeUnit","content":"Date: 19-Apr-2020\nO\nINVOICE ID INV/55-79/951\nPO Number :91\nBill to:Jason Hurst\n63567 Janice Trace Apt. 298\nWest Michaelbury, GA 26918 US\nTel:+(773)807-3019\nEmail:hthomas@example.org\nSite:https://ramirez.com/\nQty\nID\nDescription\nUnit price\nAmount\n1.00\n576324\nLater able either wrong.\n23.11\n23.11\n4.00\n334505\nStand expect.\n45.64\n182.56\n3.00\n832003\nParticularly area.\n82.95\n248.85\n6.00\n586735\nCouple open population.\n4.76\n28.56\n4.00\n866522\nProcess participant paper.\n70.44\n281.76\nSUB_TOTAL : 764.84 USD\nTAX:VAT (4.24%): 32.44 USD\nBALANCE DUE : 762.86 USD\nTotal in words: seven hundred and six-\nty-two point eight six\nNote:\nThis order is shipped through blue dart courier\nAddress:233 Foster Gardens\nJohnburgh, ID 41900 US\nBailey Group\nEmail:paul73@example.com","pages":[{"pageNumber":1,"angle":0.04318474978208542,"width":595,"height":841,"unit":"pixel","words":[{"content":"Date:","polygon":[418,40,447,40,447,54,418,53],"confidence":0.995,"span":{"offset":0,"length":5}},{"content":"19-Apr-2020","polygon":[451,40,519,39,519,54,451,54],"confidence":0.994,"span":{"offset":6,"length":11}},{"content":"O","polygon":[334,65,375,67,375,105,334,104],"confidence":0.258,"span":{"offset":18,"length":1}},{"content":"INVOICE","polygon":[418,58,468,57,468,71,418,71],"confidence":0.992,"span":{"offset":20,"length":7}},{"content":"ID","polygon":[471,57,481,57,481,71,471,71],"confidence":0.993,"span":{"offset":28,"length":2}},{"content":"INV/55-79/951","polygon":[485,57,564,57,564,71,485,71],"confidence":0.992,"span":{"offset":31,"length":13}},{"content":"PO","polygon":[417,74,433,74,433,86,417,86],"confidence":0.994,"span":{"offset":45,"length":2}},{"content":"Number","polygon":[437,74,478,74,478,86,436,86],"confidence":0.992,"span":{"offset":48,"length":6}},{"content":":91","polygon":[481,74,497,74,497,86,481,86],"confidence":0.996,"span":{"offset":55,"length":3}},{"content":"Bill","polygon":[27,127,46,127,46,140,27,140],"confidence":0.992,"span":{"offset":59,"length":4}},{"content":"to:Jason","polygon":[49,127,99,127,99,140,49,140],"confidence":0.969,"span":{"offset":64,"length":8}},{"content":"Hurst","polygon":[103,127,137,127,137,140,103,140],"confidence":0.994,"span":{"offset":73,"length":5}},{"content":"63567","polygon":[27,141,61,141,61,154,27,154],"confidence":0.995,"span":{"offset":79,"length":5}},{"content":"Janice","polygon":[64,141,102,141,102,154,64,154],"confidence":0.992,"span":{"offset":85,"length":6}},{"content":"Trace","polygon":[105,141,137,141,137,155,105,154],"confidence":0.995,"span":{"offset":92,"length":5}},{"content":"Apt.","polygon":[140,141,165,141,165,154,140,155],"confidence":0.992,"span":{"offset":98,"length":4}},{"content":"298","polygon":[168,141,189,141,189,154,168,154],"confidence":0.997,"span":{"offset":103,"length":3}},{"content":"West","polygon":[27,155,55,156,55,169,27,169],"confidence":0.992,"span":{"offset":107,"length":4}},{"content":"Michaelbury,","polygon":[58,156,133,156,133,169,58,169],"confidence":0.992,"span":{"offset":112,"length":12}},{"content":"GA","polygon":[136,156,154,156,154,169,136,169],"confidence":0.993,"span":{"offset":125,"length":2}},{"content":"26918","polygon":[158,156,191,156,191,169,158,169],"confidence":0.993,"span":{"offset":128,"length":5}},{"content":"US","polygon":[194,155,213,155,213,169,194,169],"confidence":0.995,"span":{"offset":134,"length":2}},{"content":"Tel:+(773)807-3019","polygon":[27,170,136,170,136,183,27,183],"confidence":0.975,"span":{"offset":137,"length":18}},{"content":"Email:hthomas@example.org","polygon":[27,185,198,185,198,199,27,198],"confidence":0.955,"span":{"offset":156,"length":25}},{"content":"Site:https://ramirez.com/","polygon":[27,199,169,199,169,212,27,212],"confidence":0.961,"span":{"offset":182,"length":25}},{"content":"Qty","polygon":[12,371,31,371,31,382,12,381],"confidence":0.996,"span":{"offset":208,"length":3}},{"content":"ID","polygon":[72,371,84,371,84,381,72,381],"confidence":0.992,"span":{"offset":212,"length":2}},{"content":"Description","polygon":[138,371,195,371,195,382,138,381],"confidence":0.991,"span":{"offset":215,"length":11}},{"content":"Unit","polygon":[379,370,399,371,399,382,379,382],"confidence":0.992,"span":{"offset":227,"length":4}},{"content":"price","polygon":[402,371,427,371,427,382,401,382],"confidence":0.993,"span":{"offset":232,"length":5}},{"content":"Amount","polygon":[463,371,503,371,503,381,463,381],"confidence":0.996,"span":{"offset":238,"length":6}},{"content":"1.00","polygon":[13,389,33,389,33,399,13,399],"confidence":0.992,"span":{"offset":245,"length":4}},{"content":"576324","polygon":[72,388,107,389,107,399,72,399],"confidence":0.995,"span":{"offset":250,"length":6}},{"content":"Later","polygon":[138,389,162,389,162,400,138,399],"confidence":0.996,"span":{"offset":257,"length":5}},{"content":"able","polygon":[164,389,183,389,183,400,164,400],"confidence":0.989,"span":{"offset":263,"length":4}},{"content":"either","polygon":[185,389,211,389,211,400,185,400],"confidence":0.992,"span":{"offset":268,"length":6}},{"content":"wrong.","polygon":[213,389,244,389,244,400,213,400],"confidence":0.977,"span":{"offset":275,"length":6}},{"content":"23.11","polygon":[389,388,415,388,415,399,389,399],"confidence":0.973,"span":{"offset":282,"length":5}},{"content":"23.11","polygon":[469,388,495,389,495,399,469,399],"confidence":0.93,"span":{"offset":288,"length":5}},{"content":"4.00","polygon":[12,407,33,407,33,417,12,416],"confidence":0.99,"span":{"offset":294,"length":4}},{"content":"334505","polygon":[72,406,108,406,108,417,72,417],"confidence":0.997,"span":{"offset":299,"length":6}},{"content":"Stand","polygon":[138,406,165,407,164,417,138,417],"confidence":0.995,"span":{"offset":306,"length":5}},{"content":"expect.","polygon":[167,407,201,407,201,418,167,418],"confidence":0.963,"span":{"offset":312,"length":7}},{"content":"45.64","polygon":[389,406,416,406,416,416,389,417],"confidence":0.993,"span":{"offset":320,"length":5}},{"content":"182.56","polygon":[467,407,499,407,499,417,467,417],"confidence":0.956,"span":{"offset":326,"length":6}},{"content":"3.00","polygon":[12,425,33,425,33,434,12,434],"confidence":0.991,"span":{"offset":333,"length":4}},{"content":"832003","polygon":[72,425,107,425,107,435,72,435],"confidence":0.996,"span":{"offset":338,"length":6}},{"content":"Particularly","polygon":[138,424,188,425,188,436,138,436],"confidence":0.963,"span":{"offset":345,"length":12}},{"content":"area.","polygon":[191,425,215,425,215,436,190,436],"confidence":0.935,"span":{"offset":358,"length":5}},{"content":"82.95","polygon":[389,424,416,424,416,435,389,435],"confidence":0.994,"span":{"offset":364,"length":5}},{"content":"248.85","polygon":[467,424,499,424,499,435,467,435],"confidence":0.974,"span":{"offset":370,"length":6}},{"content":"6.00","polygon":[12,443,33,443,33,453,12,452],"confidence":0.987,"span":{"offset":377,"length":4}},{"content":"586735","polygon":[72,442,107,443,107,453,72,452],"confidence":0.997,"span":{"offset":382,"length":6}},{"content":"Couple","polygon":[138,442,170,443,170,454,138,454],"confidence":0.995,"span":{"offset":389,"length":6}},{"content":"open","polygon":[173,443,195,443,195,454,173,454],"confidence":0.991,"span":{"offset":396,"length":4}},{"content":"population.","polygon":[198,443,248,442,248,454,198,454],"confidence":0.975,"span":{"offset":401,"length":11}},{"content":"4.76","polygon":[392,443,414,442,414,452,392,452],"confidence":0.989,"span":{"offset":413,"length":4}},{"content":"28.56","polygon":[469,443,496,443,496,453,469,452],"confidence":0.996,"span":{"offset":418,"length":5}},{"content":"4.00","polygon":[12,460,33,461,33,471,12,470],"confidence":0.989,"span":{"offset":424,"length":4}},{"content":"866522","polygon":[72,460,108,460,108,471,72,471],"confidence":0.997,"span":{"offset":429,"length":6}},{"content":"Process","polygon":[138,460,175,460,175,472,138,472],"confidence":0.992,"span":{"offset":436,"length":7}},{"content":"participant","polygon":[177,460,224,461,223,472,177,472],"confidence":0.985,"span":{"offset":444,"length":11}},{"content":"paper.","polygon":[226,461,255,461,255,472,226,472],"confidence":0.822,"span":{"offset":456,"length":6}},{"content":"70.44","polygon":[389,460,416,460,416,470,389,471],"confidence":0.986,"span":{"offset":463,"length":5}},{"content":"281.76","polygon":[467,460,500,460,500,471,467,471],"confidence":0.992,"span":{"offset":469,"length":6}},{"content":"SUB_TOTAL","polygon":[169,512,240,512,240,526,169,526],"confidence":0.991,"span":{"offset":476,"length":9}},{"content":":","polygon":[243,512,248,512,248,526,243,526],"confidence":0.984,"span":{"offset":486,"length":1}},{"content":"764.84","polygon":[252,512,289,512,289,526,252,526],"confidence":0.996,"span":{"offset":488,"length":6}},{"content":"USD","polygon":[296,512,322,512,322,525,295,526],"confidence":0.997,"span":{"offset":495,"length":3}},{"content":"TAX:VAT","polygon":[168,530,222,530,222,544,168,543],"confidence":0.992,"span":{"offset":499,"length":7}},{"content":"(4.24%):","polygon":[225,530,270,530,270,544,225,544],"confidence":0.67,"span":{"offset":507,"length":8}},{"content":"32.44","polygon":[278,530,308,530,308,544,278,544],"confidence":0.995,"span":{"offset":516,"length":5}},{"content":"USD","polygon":[311,530,337,530,337,544,311,544],"confidence":0.997,"span":{"offset":522,"length":3}},{"content":"BALANCE","polygon":[169,549,238,549,238,564,169,564],"confidence":0.995,"span":{"offset":526,"length":7}},{"content":"DUE","polygon":[242,549,271,549,271,563,242,564],"confidence":0.996,"span":{"offset":534,"length":3}},{"content":":","polygon":[276,549,279,549,279,563,276,563],"confidence":0.984,"span":{"offset":538,"length":1}},{"content":"762.86","polygon":[283,549,326,549,326,563,283,563],"confidence":0.995,"span":{"offset":540,"length":6}},{"content":"USD","polygon":[331,549,361,549,361,563,331,563],"confidence":0.997,"span":{"offset":547,"length":3}},{"content":"Total","polygon":[169,569,198,569,198,582,170,582],"confidence":0.995,"span":{"offset":551,"length":5}},{"content":"in","polygon":[200,569,213,569,213,582,200,582],"confidence":0.997,"span":{"offset":557,"length":2}},{"content":"words:","polygon":[216,569,255,569,255,582,216,582],"confidence":0.993,"span":{"offset":560,"length":6}},{"content":"seven","polygon":[262,569,296,569,296,582,262,582],"confidence":0.997,"span":{"offset":567,"length":5}},{"content":"hundred","polygon":[300,569,347,569,347,583,300,582],"confidence":0.994,"span":{"offset":573,"length":7}},{"content":"and","polygon":[351,569,372,569,372,582,351,583],"confidence":0.998,"span":{"offset":581,"length":3}},{"content":"six-","polygon":[376,569,398,569,398,582,376,582],"confidence":0.992,"span":{"offset":585,"length":4}},{"content":"ty-two","polygon":[169,584,206,584,206,598,169,598],"confidence":0.994,"span":{"offset":590,"length":6}},{"content":"point","polygon":[209,584,239,584,239,598,209,598],"confidence":0.998,"span":{"offset":597,"length":5}},{"content":"eight","polygon":[242,584,271,584,271,598,242,598],"confidence":0.997,"span":{"offset":603,"length":5}},{"content":"six","polygon":[274,584,293,584,293,598,274,598],"confidence":0.988,"span":{"offset":609,"length":3}},{"content":"Note:","polygon":[21,655,54,656,54,667,21,667],"confidence":0.994,"span":{"offset":613,"length":5}},{"content":"This","polygon":[21,669,46,669,46,683,21,683],"confidence":0.992,"span":{"offset":619,"length":4}},{"content":"order","polygon":[50,669,79,669,79,683,49,683],"confidence":0.995,"span":{"offset":624,"length":5}},{"content":"is","polygon":[82,669,94,669,94,683,82,683],"confidence":0.998,"span":{"offset":630,"length":2}},{"content":"shipped","polygon":[97,669,143,669,142,683,97,683],"confidence":0.996,"span":{"offset":633,"length":7}},{"content":"through","polygon":[146,669,191,669,191,683,146,683],"confidence":0.994,"span":{"offset":641,"length":7}},{"content":"blue","polygon":[195,669,220,669,219,683,195,683],"confidence":0.992,"span":{"offset":649,"length":4}},{"content":"dart","polygon":[223,669,246,669,246,683,223,683],"confidence":0.992,"span":{"offset":654,"length":4}},{"content":"courier","polygon":[249,669,292,669,292,683,249,683],"confidence":0.993,"span":{"offset":659,"length":7}},{"content":"Address:233","polygon":[267,721,339,721,339,735,266,734],"confidence":0.992,"span":{"offset":667,"length":11}},{"content":"Foster","polygon":[343,721,380,721,380,735,343,735],"confidence":0.994,"span":{"offset":679,"length":6}},{"content":"Gardens","polygon":[383,721,433,721,433,735,383,735],"confidence":0.995,"span":{"offset":686,"length":7}},{"content":"Johnburgh,","polygon":[266,736,333,736,333,749,266,750],"confidence":0.993,"span":{"offset":694,"length":10}},{"content":"ID","polygon":[337,736,349,736,349,749,337,749],"confidence":0.995,"span":{"offset":705,"length":2}},{"content":"41900","polygon":[352,736,385,736,385,749,352,749],"confidence":0.992,"span":{"offset":708,"length":5}},{"content":"US","polygon":[389,736,407,735,407,749,389,749],"confidence":0.997,"span":{"offset":714,"length":2}},{"content":"Bailey","polygon":[19,773,55,773,55,787,19,787],"confidence":0.995,"span":{"offset":717,"length":6}},{"content":"Group","polygon":[59,773,96,774,96,788,58,788],"confidence":0.998,"span":{"offset":724,"length":5}},{"content":"Email:paul73@example.com","polygon":[311,787,475,787,475,801,311,801],"confidence":0.926,"span":{"offset":730,"length":24}}],"lines":[{"content":"Date: 19-Apr-2020","polygon":[418,39,518,39,518,53,418,54],"spans":[{"offset":0,"length":17}]},{"content":"O","polygon":[334,65,374,65,374,104,334,105],"spans":[{"offset":18,"length":1}]},{"content":"INVOICE ID INV/55-79/951","polygon":[418,57,564,57,564,71,418,71],"spans":[{"offset":20,"length":24}]},{"content":"PO Number :91","polygon":[417,74,497,74,497,86,417,86],"spans":[{"offset":45,"length":13}]},{"content":"Bill to:Jason Hurst","polygon":[27,127,136,127,136,140,27,140],"spans":[{"offset":59,"length":19}]},{"content":"63567 Janice Trace Apt. 298","polygon":[27,141,188,141,188,154,27,155],"spans":[{"offset":79,"length":27}]},{"content":"West Michaelbury, GA 26918 US","polygon":[27,155,212,155,212,169,27,169],"spans":[{"offset":107,"length":29}]},{"content":"Tel:+(773)807-3019","polygon":[27,170,136,170,136,183,27,183],"spans":[{"offset":137,"length":18}]},{"content":"Email:hthomas@example.org","polygon":[27,185,197,185,197,199,27,198],"spans":[{"offset":156,"length":25}]},{"content":"Site:https://ramirez.com/","polygon":[27,199,169,199,169,212,27,212],"spans":[{"offset":182,"length":25}]},{"content":"Qty","polygon":[12,371,30,371,30,381,12,381],"spans":[{"offset":208,"length":3}]},{"content":"ID","polygon":[72,371,84,371,84,381,72,380],"spans":[{"offset":212,"length":2}]},{"content":"Description","polygon":[138,371,195,371,195,381,138,381],"spans":[{"offset":215,"length":11}]},{"content":"Unit price","polygon":[379,370,427,371,427,382,379,381],"spans":[{"offset":227,"length":10}]},{"content":"Amount","polygon":[463,371,503,371,503,381,463,381],"spans":[{"offset":238,"length":6}]},{"content":"1.00","polygon":[13,389,33,389,33,399,13,399],"spans":[{"offset":245,"length":4}]},{"content":"576324","polygon":[72,388,107,389,107,399,72,399],"spans":[{"offset":250,"length":6}]},{"content":"Later able either wrong.","polygon":[138,388,244,389,244,400,138,399],"spans":[{"offset":257,"length":24}]},{"content":"23.11","polygon":[389,388,415,388,415,399,389,399],"spans":[{"offset":282,"length":5}]},{"content":"23.11","polygon":[469,388,495,388,495,399,469,399],"spans":[{"offset":288,"length":5}]},{"content":"4.00","polygon":[12,407,33,407,33,417,12,417],"spans":[{"offset":294,"length":4}]},{"content":"334505","polygon":[72,406,108,406,108,417,72,417],"spans":[{"offset":299,"length":6}]},{"content":"Stand expect.","polygon":[138,406,200,407,200,417,138,417],"spans":[{"offset":306,"length":13}]},{"content":"45.64","polygon":[389,406,416,406,416,416,389,416],"spans":[{"offset":320,"length":5}]},{"content":"182.56","polygon":[467,406,499,406,499,417,467,417],"spans":[{"offset":326,"length":6}]},{"content":"3.00","polygon":[12,424,33,424,33,434,12,434],"spans":[{"offset":333,"length":4}]},{"content":"832003","polygon":[72,425,107,425,107,435,72,435],"spans":[{"offset":338,"length":6}]},{"content":"Particularly area.","polygon":[138,424,214,425,214,436,138,436],"spans":[{"offset":345,"length":18}]},{"content":"82.95","polygon":[389,424,416,424,416,435,389,435],"spans":[{"offset":364,"length":5}]},{"content":"248.85","polygon":[467,424,498,424,498,435,467,435],"spans":[{"offset":370,"length":6}]},{"content":"6.00","polygon":[12,443,33,443,33,453,12,452],"spans":[{"offset":377,"length":4}]},{"content":"586735","polygon":[72,442,107,443,107,452,72,452],"spans":[{"offset":382,"length":6}]},{"content":"Couple open population.","polygon":[138,442,247,442,247,454,138,454],"spans":[{"offset":389,"length":23}]},{"content":"4.76","polygon":[392,443,414,442,414,452,392,452],"spans":[{"offset":413,"length":4}]},{"content":"28.56","polygon":[469,442,496,442,496,452,469,452],"spans":[{"offset":418,"length":5}]},{"content":"4.00","polygon":[12,460,33,460,33,470,12,470],"spans":[{"offset":424,"length":4}]},{"content":"866522","polygon":[72,460,107,460,107,471,72,471],"spans":[{"offset":429,"length":6}]},{"content":"Process participant paper.","polygon":[138,460,255,461,255,472,138,472],"spans":[{"offset":436,"length":26}]},{"content":"70.44","polygon":[389,460,416,460,416,471,389,470],"spans":[{"offset":463,"length":5}]},{"content":"281.76","polygon":[467,460,499,460,499,471,467,471],"spans":[{"offset":469,"length":6}]},{"content":"SUB_TOTAL : 764.84 USD","polygon":[169,512,322,512,322,525,169,526],"spans":[{"offset":476,"length":22}]},{"content":"TAX:VAT (4.24%): 32.44 USD","polygon":[168,530,337,530,337,544,168,544],"spans":[{"offset":499,"length":26}]},{"content":"BALANCE DUE : 762.86 USD","polygon":[169,549,360,548,360,563,169,563],"spans":[{"offset":526,"length":24}]},{"content":"Total in words: seven hundred and six-","polygon":[169,569,398,569,398,582,169,582],"spans":[{"offset":551,"length":38}]},{"content":"ty-two point eight six","polygon":[169,584,292,584,292,598,169,598],"spans":[{"offset":590,"length":22}]},{"content":"Note:","polygon":[21,655,54,656,54,667,21,667],"spans":[{"offset":613,"length":5}]},{"content":"This order is shipped through blue dart courier","polygon":[21,669,292,669,292,683,21,683],"spans":[{"offset":619,"length":47}]},{"content":"Address:233 Foster Gardens","polygon":[266,721,432,721,432,735,266,734],"spans":[{"offset":667,"length":26}]},{"content":"Johnburgh, ID 41900 US","polygon":[266,736,407,735,407,749,266,749],"spans":[{"offset":694,"length":22}]},{"content":"Bailey Group","polygon":[19,773,95,774,95,788,19,787],"spans":[{"offset":717,"length":12}]},{"content":"Email:paul73@example.com","polygon":[311,787,474,787,474,801,311,801],"spans":[{"offset":730,"length":24}]}],"spans":[{"offset":0,"length":754}],"kind":"document"}],"tables":[{"rowCount":6,"columnCount":5,"cells":[{"kind":"columnHeader","rowIndex":0,"columnIndex":0,"content":"Qty","boundingRegions":[{"pageNumber":1,"polygon":[6,367,67,367,67,384,6,384]}],"spans":[{"offset":208,"length":3}]},{"kind":"columnHeader","rowIndex":0,"columnIndex":1,"content":"ID","boundingRegions":[{"pageNumber":1,"polygon":[67,367,132,367,132,384,67,384]}],"spans":[{"offset":212,"length":2}]},{"kind":"columnHeader","rowIndex":0,"columnIndex":2,"content":"Description","boundingRegions":[{"pageNumber":1,"polygon":[132,367,362,367,362,384,132,384]}],"spans":[{"offset":215,"length":11}]},{"kind":"columnHeader","rowIndex":0,"columnIndex":3,"content":"Unit price","boundingRegions":[{"pageNumber":1,"polygon":[362,367,441,367,441,384,362,384]}],"spans":[{"offset":227,"length":10}]},{"kind":"columnHeader","rowIndex":0,"columnIndex":4,"content":"Amount","boundingRegions":[{"pageNumber":1,"polygon":[441,367,521,367,521,384,441,384]}],"spans":[{"offset":238,"length":6}]},{"rowIndex":1,"columnIndex":0,"content":"1.00","boundingRegions":[{"pageNumber":1,"polygon":[6,384,67,384,67,402,6,402]}],"spans":[{"offset":245,"length":4}]},{"rowIndex":1,"columnIndex":1,"content":"576324","boundingRegions":[{"pageNumber":1,"polygon":[67,384,132,384,132,402,67,402]}],"spans":[{"offset":250,"length":6}]},{"rowIndex":1,"columnIndex":2,"content":"Later able either wrong.","boundingRegions":[{"pageNumber":1,"polygon":[132,384,362,384,362,402,132,402]}],"spans":[{"offset":257,"length":24}]},{"rowIndex":1,"columnIndex":3,"content":"23.11","boundingRegions":[{"pageNumber":1,"polygon":[362,384,441,384,441,402,362,402]}],"spans":[{"offset":282,"length":5}]},{"rowIndex":1,"columnIndex":4,"content":"23.11","boundingRegions":[{"pageNumber":1,"polygon":[441,384,521,384,521,402,441,402]}],"spans":[{"offset":288,"length":5}]},{"rowIndex":2,"columnIndex":0,"content":"4.00","boundingRegions":[{"pageNumber":1,"polygon":[6,402,67,402,67,420,6,420]}],"spans":[{"offset":294,"length":4}]},{"rowIndex":2,"columnIndex":1,"content":"334505","boundingRegions":[{"pageNumber":1,"polygon":[67,402,132,402,132,420,67,420]}],"spans":[{"offset":299,"length":6}]},{"rowIndex":2,"columnIndex":2,"content":"Stand expect.","boundingRegions":[{"pageNumber":1,"polygon":[132,402,362,402,362,420,132,420]}],"spans":[{"offset":306,"length":13}]},{"rowIndex":2,"columnIndex":3,"content":"45.64","boundingRegions":[{"pageNumber":1,"polygon":[362,402,441,402,441,420,362,420]}],"spans":[{"offset":320,"length":5}]},{"rowIndex":2,"columnIndex":4,"content":"182.56","boundingRegions":[{"pageNumber":1,"polygon":[441,402,521,402,521,420,441,420]}],"spans":[{"offset":326,"length":6}]},{"rowIndex":3,"columnIndex":0,"content":"3.00","boundingRegions":[{"pageNumber":1,"polygon":[6,420,67,420,67,438,5,438]}],"spans":[{"offset":333,"length":4}]},{"rowIndex":3,"columnIndex":1,"content":"832003","boundingRegions":[{"pageNumber":1,"polygon":[67,420,132,420,132,438,67,438]}],"spans":[{"offset":338,"length":6}]},{"rowIndex":3,"columnIndex":2,"content":"Particularly area.","boundingRegions":[{"pageNumber":1,"polygon":[132,420,362,420,362,438,132,438]}],"spans":[{"offset":345,"length":18}]},{"rowIndex":3,"columnIndex":3,"content":"82.95","boundingRegions":[{"pageNumber":1,"polygon":[362,420,441,420,441,438,362,438]}],"spans":[{"offset":364,"length":5}]},{"rowIndex":3,"columnIndex":4,"content":"248.85","boundingRegions":[{"pageNumber":1,"polygon":[441,420,521,420,521,438,441,438]}],"spans":[{"offset":370,"length":6}]},{"rowIndex":4,"columnIndex":0,"content":"6.00","boundingRegions":[{"pageNumber":1,"polygon":[5,438,67,438,67,456,5,456]}],"spans":[{"offset":377,"length":4}]},{"rowIndex":4,"columnIndex":1,"content":"586735","boundingRegions":[{"pageNumber":1,"polygon":[67,438,132,438,132,456,67,456]}],"spans":[{"offset":382,"length":6}]},{"rowIndex":4,"columnIndex":2,"content":"Couple open population.","boundingRegions":[{"pageNumber":1,"polygon":[132,438,362,438,362,456,132,456]}],"spans":[{"offset":389,"length":23}]},{"rowIndex":4,"columnIndex":3,"content":"4.76","boundingRegions":[{"pageNumber":1,"polygon":[362,438,441,438,441,456,362,456]}],"spans":[{"offset":413,"length":4}]},{"rowIndex":4,"columnIndex":4,"content":"28.56","boundingRegions":[{"pageNumber":1,"polygon":[441,438,521,438,522,456,441,456]}],"spans":[{"offset":418,"length":5}]},{"rowIndex":5,"columnIndex":0,"content":"4.00","boundingRegions":[{"pageNumber":1,"polygon":[5,456,67,456,67,474,5,474]}],"spans":[{"offset":424,"length":4}]},{"rowIndex":5,"columnIndex":1,"content":"866522","boundingRegions":[{"pageNumber":1,"polygon":[67,456,132,456,132,474,67,474]}],"spans":[{"offset":429,"length":6}]},{"rowIndex":5,"columnIndex":2,"content":"Process participant paper.","boundingRegions":[{"pageNumber":1,"polygon":[132,456,362,456,361,474,132,474]}],"spans":[{"offset":436,"length":26}]},{"rowIndex":5,"columnIndex":3,"content":"70.44","boundingRegions":[{"pageNumber":1,"polygon":[362,456,441,456,441,474,361,474]}],"spans":[{"offset":463,"length":5}]},{"rowIndex":5,"columnIndex":4,"content":"281.76","boundingRegions":[{"pageNumber":1,"polygon":[441,456,522,456,522,474,441,474]}],"spans":[{"offset":469,"length":6}]}],"boundingRegions":[{"pageNumber":1,"polygon":[4,365,524,365,524,475,4,476]}],"spans":[{"offset":208,"length":267}]}],"styles":[],"documents":[{"docType":"invoice","boundingRegions":[{"pageNumber":1,"polygon":[0,0,595,0,595,841,0,841]}],"fields":{"AmountDue":{"type":"currency","valueCurrency":{"currencySymbol":"USD","amount":762.86,"currencyCode":"USD"},"content":"762.86 USD","boundingRegions":[{"pageNumber":1,"polygon":[283,549,361,549,361,563,283,563]}],"confidence":0.937,"spans":[{"offset":540,"length":10}]},"BillingAddress":{"type":"address","content":"63567 Janice Trace Apt. 298\nWest Michaelbury, GA 26918 US","boundingRegions":[{"pageNumber":1,"polygon":[27,141,213,141,213,169,27,169]}],"confidence":0.881,"spans":[{"offset":79,"length":57}],"valueAddress":{"houseNumber":"63567","road":"Janice Trace","postalCode":"26918","city":"West Michaelbury","state":"GA","countryRegion":"US","streetAddress":"63567 Janice Trace Apt. 298","unit":"Apt. 298"}},"BillingAddressRecipient":{"type":"string","valueString":"to:Jason Hurst","content":"to:Jason Hurst","boundingRegions":[{"pageNumber":1,"polygon":[49,127,137,127,137,140,49,140]}],"confidence":0.926,"spans":[{"offset":64,"length":14}]},"CustomerName":{"type":"string","valueString":"to:Jason Hurst","content":"to:Jason Hurst","boundingRegions":[{"pageNumber":1,"polygon":[49,127,137,127,137,140,49,140]}],"confidence":0.926,"spans":[{"offset":64,"length":14}]},"InvoiceDate":{"type":"date","valueDate":"2020-04-19","content":"19-Apr-2020","boundingRegions":[{"pageNumber":1,"polygon":[451,40,519,39,519,54,451,54]}],"confidence":0.968,"spans":[{"offset":6,"length":11}]},"InvoiceId":{"type":"string","valueString":"INV/55-79/951","content":"INV/55-79/951","boundingRegions":[{"pageNumber":1,"polygon":[485,57,564,57,564,71,485,71]}],"confidence":0.969,"spans":[{"offset":31,"length":13}]},"InvoiceTotal":{"type":"currency","valueCurrency":{"currencySymbol":"USD","amount":762.86,"currencyCode":"USD"},"content":"762.86 USD","boundingRegions":[{"pageNumber":1,"polygon":[283,549,361,549,361,563,283,563]}],"confidence":0.937,"spans":[{"offset":540,"length":10}]},"Items":{"type":"array","valueArray":[{"type":"object","valueObject":{"Amount":{"type":"currency","valueCurrency":{"amount":23.11,"currencyCode":"USD"},"content":"23.11","boundingRegions":[{"pageNumber":1,"polygon":[469,388,495,389,495,399,469,399]}],"confidence":0.947,"spans":[{"offset":288,"length":5}]},"Description":{"type":"string","valueString":"Later able either wrong.","content":"Later able either wrong.","boundingRegions":[{"pageNumber":1,"polygon":[138,389,244,389,244,400,138,400]}],"confidence":0.944,"spans":[{"offset":257,"length":24}]},"ProductCode":{"type":"string","valueString":"576324","content":"576324","boundingRegions":[{"pageNumber":1,"polygon":[72,388,107,389,107,399,72,399]}],"confidence":0.669,"spans":[{"offset":250,"length":6}]},"Quantity":{"type":"number","valueNumber":1,"content":"1.00","boundingRegions":[{"pageNumber":1,"polygon":[13,389,33,389,33,399,13,399]}],"confidence":0.937,"spans":[{"offset":245,"length":4}]},"UnitPrice":{"type":"currency","valueCurrency":{"amount":23.11,"currencyCode":"USD"},"content":"23.11","boundingRegions":[{"pageNumber":1,"polygon":[389,388,415,388,415,399,389,399]}],"confidence":0.94,"spans":[{"offset":282,"length":5}]}},"content":"1.00\n576324\nLater able either wrong.\n23.11\n23.11","boundingRegions":[{"pageNumber":1,"polygon":[13,388,495,388,495,400,13,400]}],"confidence":0.951,"spans":[{"offset":245,"length":48}]},{"type":"object","valueObject":{"Amount":{"type":"currency","valueCurrency":{"amount":182.56,"currencyCode":"USD"},"content":"182.56","boundingRegions":[{"pageNumber":1,"polygon":[467,407,499,407,499,417,467,417]}],"confidence":0.944,"spans":[{"offset":326,"length":6}]},"Description":{"type":"string","valueString":"Stand expect.","content":"Stand expect.","boundingRegions":[{"pageNumber":1,"polygon":[138,406,201,407,201,419,138,417]}],"confidence":0.943,"spans":[{"offset":306,"length":13}]},"ProductCode":{"type":"string","valueString":"334505","content":"334505","boundingRegions":[{"pageNumber":1,"polygon":[72,406,108,406,108,417,72,417]}],"confidence":0.511,"spans":[{"offset":299,"length":6}]},"Quantity":{"type":"number","valueNumber":4,"content":"4.00","boundingRegions":[{"pageNumber":1,"polygon":[12,407,33,407,33,417,12,416]}],"confidence":0.938,"spans":[{"offset":294,"length":4}]},"UnitPrice":{"type":"currency","valueCurrency":{"amount":45.64,"currencyCode":"USD"},"content":"45.64","boundingRegions":[{"pageNumber":1,"polygon":[389,406,416,406,416,416,389,417]}],"confidence":0.938,"spans":[{"offset":320,"length":5}]}},"content":"4.00\n334505\nStand expect.\n45.64\n182.56","boundingRegions":[{"pageNumber":1,"polygon":[12,406,499,406,499,418,12,418]}],"confidence":0.949,"spans":[{"offset":294,"length":38}]},{"type":"object","valueObject":{"Amount":{"type":"currency","valueCurrency":{"amount":248.85,"currencyCode":"USD"},"content":"248.85","boundingRegions":[{"pageNumber":1,"polygon":[467,424,499,424,499,435,467,435]}],"confidence":0.943,"spans":[{"offset":370,"length":6}]},"Description":{"type":"string","valueString":"Particularly area.","content":"Particularly area.","boundingRegions":[{"pageNumber":1,"polygon":[138,424,215,425,215,437,138,436]}],"confidence":0.945,"spans":[{"offset":345,"length":18}]},"ProductCode":{"type":"string","valueString":"832003","content":"832003","boundingRegions":[{"pageNumber":1,"polygon":[72,425,107,425,107,435,72,435]}],"confidence":0.522,"spans":[{"offset":338,"length":6}]},"Quantity":{"type":"number","valueNumber":3,"content":"3.00","boundingRegions":[{"pageNumber":1,"polygon":[12,425,33,425,33,434,12,434]}],"confidence":0.937,"spans":[{"offset":333,"length":4}]},"UnitPrice":{"type":"currency","valueCurrency":{"amount":82.95,"currencyCode":"USD"},"content":"82.95","boundingRegions":[{"pageNumber":1,"polygon":[389,424,416,424,416,435,389,435]}],"confidence":0.938,"spans":[{"offset":364,"length":5}]}},"content":"3.00\n832003\nParticularly area.\n82.95\n248.85","boundingRegions":[{"pageNumber":1,"polygon":[12,424,499,424,499,436,12,436]}],"confidence":0.949,"spans":[{"offset":333,"length":43}]},{"type":"object","valueObject":{"Amount":{"type":"currency","valueCurrency":{"amount":28.56,"currencyCode":"USD"},"content":"28.56","boundingRegions":[{"pageNumber":1,"polygon":[469,443,496,443,496,453,469,452]}],"confidence":0.938,"spans":[{"offset":418,"length":5}]},"Description":{"type":"string","valueString":"Couple open population.","content":"Couple open population.","boundingRegions":[{"pageNumber":1,"polygon":[138,442,248,442,248,454,138,454]}],"confidence":0.943,"spans":[{"offset":389,"length":23}]},"ProductCode":{"type":"string","valueString":"586735","content":"586735","boundingRegions":[{"pageNumber":1,"polygon":[72,442,107,443,107,453,72,452]}],"confidence":0.658,"spans":[{"offset":382,"length":6}]},"Quantity":{"type":"number","valueNumber":6,"content":"6.00","boundingRegions":[{"pageNumber":1,"polygon":[12,443,33,443,33,453,12,452]}],"confidence":0.938,"spans":[{"offset":377,"length":4}]},"UnitPrice":{"type":"currency","valueCurrency":{"amount":4.76,"currencyCode":"USD"},"content":"4.76","boundingRegions":[{"pageNumber":1,"polygon":[392,443,414,442,414,452,392,452]}],"confidence":0.939,"spans":[{"offset":413,"length":4}]}},"content":"6.00\n586735\nCouple open population.\n4.76\n28.56","boundingRegions":[{"pageNumber":1,"polygon":[12,435,496,443,496,460,12,453]}],"confidence":0.951,"spans":[{"offset":377,"length":46}]},{"type":"object","valueObject":{"Amount":{"type":"currency","valueCurrency":{"amount":281.76,"currencyCode":"USD"},"content":"281.76","boundingRegions":[{"pageNumber":1,"polygon":[467,460,500,460,500,471,467,471]}],"confidence":0.939,"spans":[{"offset":469,"length":6}]},"Description":{"type":"string","valueString":"Process participant paper.","content":"Process participant paper.","boundingRegions":[{"pageNumber":1,"polygon":[138,460,255,460,255,472,138,472]}],"confidence":0.948,"spans":[{"offset":436,"length":26}]},"ProductCode":{"type":"string","valueString":"866522","content":"866522","boundingRegions":[{"pageNumber":1,"polygon":[72,460,108,460,108,471,72,471]}],"confidence":0.513,"spans":[{"offset":429,"length":6}]},"Quantity":{"type":"number","valueNumber":4,"content":"4.00","boundingRegions":[{"pageNumber":1,"polygon":[12,460,33,461,33,471,12,470]}],"confidence":0.937,"spans":[{"offset":424,"length":4}]},"UnitPrice":{"type":"currency","valueCurrency":{"amount":70.44,"currencyCode":"USD"},"content":"70.44","boundingRegions":[{"pageNumber":1,"polygon":[389,460,416,460,416,470,389,471]}],"confidence":0.939,"spans":[{"offset":463,"length":5}]}},"content":"4.00\n866522\nProcess participant paper.\n70.44\n281.76","boundingRegions":[{"pageNumber":1,"polygon":[12,460,500,460,500,472,12,472]}],"confidence":0.95,"spans":[{"offset":424,"length":51}]}]},"PurchaseOrder":{"type":"string","valueString":":91","content":":91","boundingRegions":[{"pageNumber":1,"polygon":[481,74,497,74,497,86,481,86]}],"confidence":0.95,"spans":[{"offset":55,"length":3}]},"SubTotal":{"type":"currency","valueCurrency":{"currencySymbol":"USD","amount":764.84,"currencyCode":"USD"},"content":"764.84 USD","boundingRegions":[{"pageNumber":1,"polygon":[252,512,322,512,322,526,252,526]}],"confidence":0.942,"spans":[{"offset":488,"length":10}]},"TaxDetails":{"type":"array","valueArray":[{"type":"object","valueObject":{"Amount":{"type":"currency","content":"USD","boundingRegions":[{"pageNumber":1,"polygon":[311,530,337,530,337,544,311,544]}],"confidence":0.38,"spans":[{"offset":522,"length":3}]},"Rate":{"type":"string","valueString":"(4.24%):","content":"(4.24%):","boundingRegions":[{"pageNumber":1,"polygon":[225,530,270,530,270,544,225,544]}],"confidence":0.792,"spans":[{"offset":507,"length":8}]}},"content":"TAX:VAT (4.24%): 32.44 USD","boundingRegions":[{"pageNumber":1,"polygon":[168,530,337,530,337,544,168,544]}],"confidence":0.311,"spans":[{"offset":499,"length":26}]}]},"TotalTax":{"type":"currency","valueCurrency":{"currencySymbol":"USD","amount":32.44,"currencyCode":"USD"},"content":"32.44 USD","boundingRegions":[{"pageNumber":1,"polygon":[278,530,337,530,337,544,278,544]}],"confidence":0.938,"spans":[{"offset":516,"length":9}]},"VendorAddress":{"type":"address","content":"Address:233 Foster Gardens\nJohnburgh, ID 41900 US","boundingRegions":[{"pageNumber":1,"polygon":[266,721,433,721,433,750,266,750]}],"confidence":0.711,"spans":[{"offset":667,"length":49}],"valueAddress":{"houseNumber":"233","road":"Foster Gardens","postalCode":"41900","city":"Johnburgh","state":"ID","countryRegion":"US","streetAddress":"233 Foster Gardens","house":"Address"}},"VendorAddressRecipient":{"type":"string","valueString":"Bailey Group","content":"Bailey Group","boundingRegions":[{"pageNumber":1,"polygon":[19,772,96,773,96,789,19,787]}],"confidence":0.917,"spans":[{"offset":717,"length":12}]},"VendorName":{"type":"string","valueString":"Bailey Group","content":"Bailey Group","boundingRegions":[{"pageNumber":1,"polygon":[19,772,96,773,96,789,19,787]}],"confidence":0.917,"spans":[{"offset":717,"length":12}]}},"confidence":1,"spans":[{"offset":0,"length":754}]}],"contentFormat":"text"}}