{
    "file_name": "Template1_Instance10.jpg",
    "ground_truth": "{\"gt_parse\": {\"buyer\": \"Angel Bailey\", \"address\": \"265 Ochoa Manors Apt. 518 North John, MD 41885 US\", \"date\": \"12-Mar-2009\", \"shopping_or_tax\": true, \"currency\": \"EUR\", \"subtotal\": 735.29, \"discount\": 26.99, \"tax\": 22.77, \"total\": 744.38}}",
    "original_data": {
        "buyer": "Angel Bailey",
        "address": "265 Ochoa Manors Apt. 518 North John, MD 41885 US",
        "date": "12-Mar-2009",
        "shopping_or_tax": true,
        "currency": "EUR",
        "subtotal": 735.29,
        "discount": 26.99,
        "tax": 22.77,
        "total": 744.38
    }
}