{
    "file_name": "Template8_Instance185.jpg",
    "ground_truth": "{\"gt_parse\": {\"buyer\": \"Cindy Williams\", \"address\": \"384 Brianna Lock Suite 483 Patricialand, NC 40739 US\", \"date\": \"05-Apr-2002\", \"shopping_or_tax\": true, \"currency\": \"USD\", \"subtotal\": 168.77, \"discount\": null, \"tax\": null, \"total\": 167.51}}",
    "original_data": {
        "buyer": "Cindy Williams",
        "address": "384 Brianna Lock Suite 483 Patricialand, NC 40739 US",
        "date": "05-Apr-2002",
        "shopping_or_tax": true,
        "currency": "USD",
        "subtotal": 168.77,
        "discount": null,
        "tax": null,
        "total": 167.51
    }
}