{
    "file_name": "Template6_Instance94.jpg",
    "ground_truth": "{\"gt_parse\": {\"buyer\": \"Brianna Clarke\", \"address\": \"589 Andrew Mission Youngshire, ME 31998 US\", \"date\": \"04-Jul-1998\", \"shopping_or_tax\": false, \"currency\": \"EUR\", \"subtotal\": 650.17, \"discount\": null, \"tax\": 19.93, \"total\": 661.58}}",
    "original_data": {
        "buyer": "Brianna Clarke",
        "address": "589 Andrew Mission Youngshire, ME 31998 US",
        "date": "04-Jul-1998",
        "shopping_or_tax": false,
        "currency": "EUR",
        "subtotal": 650.17,
        "discount": null,
        "tax": 19.93,
        "total": 661.58
    }
}