{
    "file_name": "Template5_Instance159.jpg",
    "ground_truth": "{\"gt_parse\": {\"buyer\": \"Kellie Patterson\", \"address\": \"7763 Robert Squares Suite 193 North Davidland, TN 78394 US\", \"date\": \"28-Sep-1998\", \"shopping_or_tax\": false, \"currency\": \"USD\", \"subtotal\": 192.2, \"discount\": null, \"tax\": 10.19, \"total\": 199.47}}",
    "original_data": {
        "buyer": "Kellie Patterson",
        "address": "7763 Robert Squares Suite 193 North Davidland, TN 78394 US",
        "date": "28-Sep-1998",
        "shopping_or_tax": false,
        "currency": "USD",
        "subtotal": 192.2,
        "discount": null,
        "tax": 10.19,
        "total": 199.47
    }
}