{"status":"succeeded","createdDateTime":"2025-04-03T07:32:29Z","lastUpdatedDateTime":"2025-04-03T07:32:29Z","analyzeResult":{"apiVersion":"2099-01-01-preview","modelId":"prebuilt-invoice","stringIndexType":"utf16CodeUnit","content":"Graham, Carrillo and Stark\nAddress:8110 Lee Haven\nHUSENA\nWest Michele, IN 23979 US\nwww.GrahamCarrilloandStark.com\nBILISTARE\nEmail:ghodges@example.org\nGSTIN : 24HDE7487RESRT4\nINVOICE # INV39980470\nInvoice Date: 12-Dec-1993\nBill to: Amy Taylor\n18179 Davis Glen\nKevinside, NV 48634 US\nTel:+(726)336-1467\nDue Date : 14-Nov-2022\nEmail:timothy93@example.com\nSite:https://www.martinez.com/\nSHIP_TO:\nJordan Dickerson\n48293 Amanda Meadows\nSpencerport, MO 84516 US\nTel:+(978)850-6997\nEmail:vsmith@example.org\nSite:http://neal.com/\nITEMS\nQUANTITY\nPRICE\nCareer score point.\n6.00\n$11.15\nCan party bring.\n1.00\n$22.17\nShoulder despite could popular.\n6.00\n$87.14\nAllow expert.\n1.00\n$86.42\nSUB_TOTAL : 698.33 $\nTOTAL : 717.43 $\nTotal in words: seven hundred and seve-\nnteen point four three\nBank Name\nCentral Bank of England\nBranch Name\nRaf CAMP\nBank Account Number 18957993\nBank Swift Code\nSBININBB250\nTerms & Conditions\n1. Please send payment within 8 days of receiving this invoice.\nThere will be a 2.5% interest charge per month on late invoices.\n2. Please include the Invoice number in your payment notes.","pages":[{"pageNumber":1,"angle":0.0541912317276001,"width":595,"height":841,"unit":"pixel","words":[{"content":"Graham,","polygon":[2,20,52,20,52,34,2,33],"confidence":0.994,"span":{"offset":0,"length":7}},{"content":"Carrillo","polygon":[55,20,97,20,97,33,55,34],"confidence":0.994,"span":{"offset":8,"length":8}},{"content":"and","polygon":[100,20,121,20,121,33,100,33],"confidence":0.999,"span":{"offset":17,"length":3}},{"content":"Stark","polygon":[124,20,157,20,157,33,124,33],"confidence":0.997,"span":{"offset":21,"length":5}},{"content":"Address:8110","polygon":[3,51,82,50,82,63,3,63],"confidence":0.99,"span":{"offset":27,"length":12}},{"content":"Lee","polygon":[86,50,106,50,106,63,86,63],"confidence":0.998,"span":{"offset":40,"length":3}},{"content":"Haven","polygon":[110,50,147,51,147,63,110,63],"confidence":0.997,"span":{"offset":44,"length":5}},{"content":"HUSENA","polygon":[526,44,572,43,571,52,527,53],"confidence":0.531,"span":{"offset":50,"length":6}},{"content":"West","polygon":[3,65,32,65,32,77,3,77],"confidence":0.992,"span":{"offset":57,"length":4}},{"content":"Michele,","polygon":[36,65,83,65,83,77,36,77],"confidence":0.993,"span":{"offset":62,"length":8}},{"content":"IN","polygon":[86,65,98,65,98,77,86,77],"confidence":0.994,"span":{"offset":71,"length":2}},{"content":"23979","polygon":[102,65,135,64,135,77,102,77],"confidence":0.995,"span":{"offset":74,"length":5}},{"content":"US","polygon":[138,64,157,64,157,77,138,77],"confidence":0.995,"span":{"offset":80,"length":2}},{"content":"www.GrahamCarrilloandStark.com","polygon":[247,67,447,68,447,80,247,80],"confidence":0.977,"span":{"offset":83,"length":30}},{"content":"BILISTARE","polygon":[534,63,569,63,569,72,533,72],"confidence":0.099,"span":{"offset":114,"length":9}},{"content":"Email:ghodges@example.org","polygon":[247,85,418,85,418,100,247,99],"confidence":0.981,"span":{"offset":124,"length":25}},{"content":"GSTIN","polygon":[2,107,39,107,39,120,2,120],"confidence":0.993,"span":{"offset":150,"length":5}},{"content":":","polygon":[43,107,46,107,46,120,43,120],"confidence":0.992,"span":{"offset":156,"length":1}},{"content":"24HDE7487RESRT4","polygon":[50,107,165,107,165,119,50,120],"confidence":0.992,"span":{"offset":158,"length":15}},{"content":"INVOICE","polygon":[239,130,290,131,290,144,240,144],"confidence":0.992,"span":{"offset":174,"length":7}},{"content":"#","polygon":[293,131,300,131,300,144,293,144],"confidence":0.988,"span":{"offset":182,"length":1}},{"content":"INV39980470","polygon":[304,131,378,131,378,144,304,144],"confidence":0.993,"span":{"offset":184,"length":11}},{"content":"Invoice","polygon":[437,128,476,128,476,141,437,141],"confidence":0.961,"span":{"offset":196,"length":7}},{"content":"Date:","polygon":[480,128,508,128,508,141,480,141],"confidence":0.993,"span":{"offset":204,"length":5}},{"content":"12-Dec-1993","polygon":[512,128,583,128,583,141,512,141],"confidence":0.993,"span":{"offset":210,"length":11}},{"content":"Bill","polygon":[0,143,18,143,18,156,0,155],"confidence":0.992,"span":{"offset":222,"length":4}},{"content":"to:","polygon":[22,143,34,143,34,156,21,156],"confidence":0.992,"span":{"offset":227,"length":3}},{"content":"Amy","polygon":[37,143,63,143,63,156,37,156],"confidence":0.998,"span":{"offset":231,"length":3}},{"content":"Taylor","polygon":[66,143,104,143,104,156,66,156],"confidence":0.994,"span":{"offset":235,"length":6}},{"content":"18179","polygon":[0,158,33,157,33,170,0,170],"confidence":0.995,"span":{"offset":242,"length":5}},{"content":"Davis","polygon":[37,157,68,158,68,170,37,170],"confidence":0.996,"span":{"offset":248,"length":5}},{"content":"Glen","polygon":[72,158,100,158,100,170,72,170],"confidence":0.989,"span":{"offset":254,"length":4}},{"content":"Kevinside,","polygon":[0,172,59,172,59,184,0,184],"confidence":0.992,"span":{"offset":259,"length":10}},{"content":"NV","polygon":[63,172,80,172,80,185,63,184],"confidence":0.996,"span":{"offset":270,"length":2}},{"content":"48634","polygon":[83,172,116,171,116,184,83,185],"confidence":0.995,"span":{"offset":273,"length":5}},{"content":"US","polygon":[120,171,138,171,138,184,120,184],"confidence":0.995,"span":{"offset":279,"length":2}},{"content":"Tel:+(726)336-1467","polygon":[0,186,108,186,108,199,0,199],"confidence":0.984,"span":{"offset":282,"length":18}},{"content":"Due","polygon":[438,182,462,182,462,195,438,195],"confidence":0.997,"span":{"offset":301,"length":3}},{"content":"Date","polygon":[466,182,491,182,491,195,466,195],"confidence":0.992,"span":{"offset":305,"length":4}},{"content":":","polygon":[495,182,498,182,498,195,495,195],"confidence":0.992,"span":{"offset":310,"length":1}},{"content":"14-Nov-2022","polygon":[502,182,575,182,575,195,502,195],"confidence":0.992,"span":{"offset":312,"length":11}},{"content":"Email:timothy93@example.com","polygon":[1,201,181,201,181,214,1,213],"confidence":0.847,"span":{"offset":324,"length":27}},{"content":"Site:https://www.martinez.com/","polygon":[1,215,180,215,180,228,1,228],"confidence":0.954,"span":{"offset":352,"length":30}},{"content":"SHIP_TO:","polygon":[1,240,52,241,52,253,1,252],"confidence":0.962,"span":{"offset":383,"length":8}},{"content":"Jordan","polygon":[1,254,37,254,37,266,1,265],"confidence":0.996,"span":{"offset":392,"length":6}},{"content":"Dickerson","polygon":[41,254,95,254,95,266,40,266],"confidence":0.994,"span":{"offset":399,"length":9}},{"content":"48293","polygon":[1,267,31,267,31,279,1,279],"confidence":0.995,"span":{"offset":409,"length":5}},{"content":"Amanda","polygon":[34,267,77,267,77,279,34,279],"confidence":0.995,"span":{"offset":415,"length":6}},{"content":"Meadows","polygon":[81,267,132,267,132,279,81,279],"confidence":0.997,"span":{"offset":422,"length":7}},{"content":"Spencerport,","polygon":[1,281,68,280,68,293,1,293],"confidence":0.991,"span":{"offset":430,"length":12}},{"content":"MO","polygon":[72,280,89,280,89,293,72,293],"confidence":0.995,"span":{"offset":443,"length":2}},{"content":"84516","polygon":[92,280,123,280,123,292,92,292],"confidence":0.994,"span":{"offset":446,"length":5}},{"content":"US","polygon":[126,280,143,280,143,292,126,292],"confidence":0.994,"span":{"offset":452,"length":2}},{"content":"Tel:+(978)850-6997","polygon":[1,293,100,293,100,305,1,305],"confidence":0.962,"span":{"offset":455,"length":18}},{"content":"Email:vsmith@example.org","polygon":[1,307,146,307,146,320,1,319],"confidence":0.925,"span":{"offset":474,"length":24}},{"content":"Site:http://neal.com/","polygon":[1,320,108,320,108,332,1,332],"confidence":0.963,"span":{"offset":499,"length":21}},{"content":"ITEMS","polygon":[109,465,142,465,142,475,109,475],"confidence":0.993,"span":{"offset":521,"length":5}},{"content":"QUANTITY","polygon":[299,465,351,465,351,476,299,476],"confidence":0.995,"span":{"offset":527,"length":8}},{"content":"PRICE","polygon":[459,465,491,465,491,475,459,475],"confidence":0.995,"span":{"offset":536,"length":5}},{"content":"Career","polygon":[82,484,113,484,113,494,82,494],"confidence":0.994,"span":{"offset":542,"length":6}},{"content":"score","polygon":[115,484,140,484,140,494,115,494],"confidence":0.996,"span":{"offset":549,"length":5}},{"content":"point.","polygon":[142,484,168,484,168,494,142,494],"confidence":0.991,"span":{"offset":555,"length":6}},{"content":"6.00","polygon":[314,484,336,484,336,493,314,493],"confidence":0.989,"span":{"offset":562,"length":4}},{"content":"$11.15","polygon":[458,483,492,483,492,494,458,494],"confidence":0.636,"span":{"offset":567,"length":6}},{"content":"Can","polygon":[89,502,107,502,107,513,88,513],"confidence":0.997,"span":{"offset":574,"length":3}},{"content":"party","polygon":[110,502,133,502,132,513,110,513],"confidence":0.994,"span":{"offset":578,"length":5}},{"content":"bring.","polygon":[135,502,161,502,161,513,135,513],"confidence":0.993,"span":{"offset":584,"length":6}},{"content":"1.00","polygon":[314,502,335,502,335,511,314,511],"confidence":0.989,"span":{"offset":591,"length":4}},{"content":"$22.17","polygon":[458,501,491,501,491,512,458,512],"confidence":0.994,"span":{"offset":596,"length":6}},{"content":"Shoulder","polygon":[53,519,95,519,94,531,53,530],"confidence":0.992,"span":{"offset":603,"length":8}},{"content":"despite","polygon":[97,519,129,519,129,531,97,531],"confidence":0.992,"span":{"offset":612,"length":7}},{"content":"could","polygon":[132,519,156,519,156,531,132,531],"confidence":0.995,"span":{"offset":620,"length":5}},{"content":"popular.","polygon":[159,519,196,519,196,531,159,531],"confidence":0.962,"span":{"offset":626,"length":8}},{"content":"6.00","polygon":[314,520,335,520,335,529,314,529],"confidence":0.983,"span":{"offset":635,"length":4}},{"content":"$87.14","polygon":[458,519,491,519,491,529,458,530],"confidence":0.995,"span":{"offset":640,"length":6}},{"content":"Allow","polygon":[95,538,120,538,120,548,95,548],"confidence":0.995,"span":{"offset":647,"length":5}},{"content":"expert.","polygon":[122,538,154,538,154,548,122,548],"confidence":0.935,"span":{"offset":653,"length":7}},{"content":"1.00","polygon":[315,538,335,538,335,547,315,547],"confidence":0.989,"span":{"offset":661,"length":4}},{"content":"$86.42","polygon":[458,537,491,537,491,547,458,547],"confidence":0.992,"span":{"offset":666,"length":6}},{"content":"SUB_TOTAL","polygon":[432,563,504,563,504,577,432,577],"confidence":0.976,"span":{"offset":673,"length":9}},{"content":":","polygon":[508,563,511,563,511,577,508,577],"confidence":0.992,"span":{"offset":683,"length":1}},{"content":"698.33","polygon":[515,563,552,563,552,577,515,577],"confidence":0.994,"span":{"offset":685,"length":6}},{"content":"$","polygon":[558,563,567,563,567,577,558,577],"confidence":0.963,"span":{"offset":692,"length":1}},{"content":"TOTAL","polygon":[353,595,395,596,395,608,353,608],"confidence":0.994,"span":{"offset":694,"length":5}},{"content":":","polygon":[398,596,401,596,401,608,398,608],"confidence":0.975,"span":{"offset":700,"length":1}},{"content":"717.43","polygon":[405,596,442,596,442,608,405,608],"confidence":0.997,"span":{"offset":702,"length":6}},{"content":"$","polygon":[445,596,454,596,454,608,445,608],"confidence":0.988,"span":{"offset":709,"length":1}},{"content":"Total","polygon":[118,617,147,617,147,629,118,629],"confidence":0.995,"span":{"offset":711,"length":5}},{"content":"in","polygon":[151,617,161,617,161,629,151,629],"confidence":0.998,"span":{"offset":717,"length":2}},{"content":"words:","polygon":[164,617,205,617,205,629,164,629],"confidence":0.993,"span":{"offset":720,"length":6}},{"content":"seven","polygon":[210,617,244,617,244,629,210,629],"confidence":0.996,"span":{"offset":727,"length":5}},{"content":"hundred","polygon":[248,617,296,617,295,629,248,629],"confidence":0.993,"span":{"offset":733,"length":7}},{"content":"and","polygon":[299,617,320,617,320,629,299,629],"confidence":0.997,"span":{"offset":741,"length":3}},{"content":"seve-","polygon":[324,617,357,617,357,629,324,629],"confidence":0.994,"span":{"offset":745,"length":5}},{"content":"nteen","polygon":[118,632,150,632,150,644,118,644],"confidence":0.994,"span":{"offset":751,"length":5}},{"content":"point","polygon":[154,632,183,632,183,644,154,644],"confidence":0.995,"span":{"offset":757,"length":5}},{"content":"four","polygon":[186,632,210,632,210,644,186,644],"confidence":0.995,"span":{"offset":763,"length":4}},{"content":"three","polygon":[213,632,244,632,244,644,213,644],"confidence":0.997,"span":{"offset":768,"length":5}},{"content":"Bank","polygon":[2,660,31,660,31,672,2,671],"confidence":0.984,"span":{"offset":774,"length":4}},{"content":"Name","polygon":[35,660,69,660,69,671,35,671],"confidence":0.992,"span":{"offset":779,"length":4}},{"content":"Central","polygon":[103,659,145,659,144,672,103,672],"confidence":0.994,"span":{"offset":784,"length":7}},{"content":"Bank","polygon":[149,659,178,659,178,672,149,672],"confidence":0.992,"span":{"offset":792,"length":4}},{"content":"of","polygon":[181,659,193,659,193,672,181,672],"confidence":0.996,"span":{"offset":797,"length":2}},{"content":"England","polygon":[196,659,245,659,245,672,196,673],"confidence":0.995,"span":{"offset":800,"length":7}},{"content":"Branch","polygon":[2,674,43,674,43,686,2,686],"confidence":0.998,"span":{"offset":808,"length":6}},{"content":"Name","polygon":[47,674,81,674,81,686,47,686],"confidence":0.989,"span":{"offset":815,"length":4}},{"content":"Raf","polygon":[112,674,132,674,132,686,112,686],"confidence":0.994,"span":{"offset":820,"length":3}},{"content":"CAMP","polygon":[135,674,171,674,171,686,135,686],"confidence":0.992,"span":{"offset":824,"length":4}},{"content":"Bank","polygon":[2,689,31,689,31,700,2,700],"confidence":0.992,"span":{"offset":829,"length":4}},{"content":"Account","polygon":[34,689,82,688,82,701,34,700],"confidence":0.996,"span":{"offset":834,"length":7}},{"content":"Number","polygon":[86,688,131,688,131,700,86,701],"confidence":0.996,"span":{"offset":842,"length":6}},{"content":"18957993","polygon":[138,688,192,688,192,700,138,700],"confidence":0.997,"span":{"offset":849,"length":8}},{"content":"Bank","polygon":[2,703,31,703,31,715,2,715],"confidence":0.986,"span":{"offset":858,"length":4}},{"content":"Swift","polygon":[35,703,63,703,63,715,35,715],"confidence":0.997,"span":{"offset":863,"length":5}},{"content":"Code","polygon":[66,703,98,703,98,715,66,715],"confidence":0.992,"span":{"offset":869,"length":4}},{"content":"SBININBB250","polygon":[115,703,196,703,196,715,115,715],"confidence":0.992,"span":{"offset":874,"length":11}},{"content":"Terms","polygon":[1,742,30,742,30,753,1,753],"confidence":0.994,"span":{"offset":886,"length":5}},{"content":"&","polygon":[33,742,40,742,40,753,33,753],"confidence":0.985,"span":{"offset":892,"length":1}},{"content":"Conditions","polygon":[43,742,97,742,97,753,43,753],"confidence":0.992,"span":{"offset":894,"length":10}},{"content":"1.","polygon":[1,755,9,755,9,765,1,765],"confidence":0.991,"span":{"offset":905,"length":2}},{"content":"Please","polygon":[12,755,43,754,43,765,12,765],"confidence":0.995,"span":{"offset":908,"length":6}},{"content":"send","polygon":[46,754,69,754,69,766,46,766],"confidence":0.99,"span":{"offset":915,"length":4}},{"content":"payment","polygon":[72,754,114,754,114,765,72,766],"confidence":0.994,"span":{"offset":920,"length":7}},{"content":"within","polygon":[116,754,145,754,145,765,116,765],"confidence":0.993,"span":{"offset":928,"length":6}},{"content":"8","polygon":[148,754,153,754,153,765,148,765],"confidence":0.977,"span":{"offset":935,"length":1}},{"content":"days","polygon":[156,754,179,754,179,766,156,765],"confidence":0.992,"span":{"offset":937,"length":4}},{"content":"of","polygon":[182,754,192,754,192,766,182,766],"confidence":0.998,"span":{"offset":942,"length":2}},{"content":"receiving","polygon":[194,754,237,754,237,766,194,766],"confidence":0.994,"span":{"offset":945,"length":9}},{"content":"this","polygon":[240,754,258,754,258,765,240,766],"confidence":0.992,"span":{"offset":955,"length":4}},{"content":"invoice.","polygon":[261,754,299,754,299,765,261,765],"confidence":0.992,"span":{"offset":960,"length":8}},{"content":"There","polygon":[1,766,28,766,28,777,1,777],"confidence":0.995,"span":{"offset":969,"length":5}},{"content":"will","polygon":[30,766,46,766,46,777,30,777],"confidence":0.995,"span":{"offset":975,"length":4}},{"content":"be","polygon":[49,766,61,766,61,777,49,777],"confidence":0.997,"span":{"offset":980,"length":2}},{"content":"a","polygon":[64,766,69,766,69,777,64,777],"confidence":0.993,"span":{"offset":983,"length":1}},{"content":"2.5%","polygon":[72,766,95,766,95,777,72,777],"confidence":0.992,"span":{"offset":985,"length":4}},{"content":"interest","polygon":[98,766,134,766,134,777,98,777],"confidence":0.993,"span":{"offset":990,"length":8}},{"content":"charge","polygon":[136,766,169,766,169,777,136,777],"confidence":0.996,"span":{"offset":999,"length":6}},{"content":"per","polygon":[172,766,188,766,188,777,172,777],"confidence":0.997,"span":{"offset":1006,"length":3}},{"content":"month","polygon":[191,766,221,766,221,777,191,777],"confidence":0.997,"span":{"offset":1010,"length":5}},{"content":"on","polygon":[224,766,236,766,236,777,224,777],"confidence":0.995,"span":{"offset":1016,"length":2}},{"content":"late","polygon":[239,766,256,766,256,777,239,777],"confidence":0.99,"span":{"offset":1019,"length":4}},{"content":"invoices.","polygon":[259,766,303,767,303,777,259,777],"confidence":0.992,"span":{"offset":1024,"length":9}},{"content":"2.","polygon":[1,778,9,778,9,789,1,789],"confidence":0.992,"span":{"offset":1034,"length":2}},{"content":"Please","polygon":[12,778,42,778,42,789,12,789],"confidence":0.994,"span":{"offset":1037,"length":6}},{"content":"include","polygon":[45,778,81,778,81,789,45,789],"confidence":0.992,"span":{"offset":1044,"length":7}},{"content":"the","polygon":[84,778,98,778,98,789,84,789],"confidence":0.998,"span":{"offset":1052,"length":3}},{"content":"Invoice","polygon":[100,778,136,778,136,789,100,789],"confidence":0.974,"span":{"offset":1056,"length":7}},{"content":"number","polygon":[139,778,176,778,176,790,139,789],"confidence":0.996,"span":{"offset":1064,"length":6}},{"content":"in","polygon":[178,778,187,778,187,790,178,790],"confidence":0.995,"span":{"offset":1071,"length":2}},{"content":"your","polygon":[190,778,212,778,212,790,190,790],"confidence":0.995,"span":{"offset":1074,"length":4}},{"content":"payment","polygon":[215,778,256,778,256,790,215,790],"confidence":0.992,"span":{"offset":1079,"length":7}},{"content":"notes.","polygon":[258,778,289,778,289,789,258,790],"confidence":0.99,"span":{"offset":1087,"length":6}}],"lines":[{"content":"Graham, Carrillo and Stark","polygon":[2,20,156,20,156,33,2,33],"spans":[{"offset":0,"length":26}]},{"content":"Address:8110 Lee Haven","polygon":[3,50,147,50,147,63,3,63],"spans":[{"offset":27,"length":22}]},{"content":"HUSENA","polygon":[526,43,572,42,572,52,527,53],"spans":[{"offset":50,"length":6}]},{"content":"West Michele, IN 23979 US","polygon":[3,65,157,64,157,77,3,78],"spans":[{"offset":57,"length":25}]},{"content":"www.GrahamCarrilloandStark.com","polygon":[247,67,447,67,447,80,247,80],"spans":[{"offset":83,"length":30}]},{"content":"BILISTARE","polygon":[533,63,569,63,569,74,533,74],"spans":[{"offset":114,"length":9}]},{"content":"Email:ghodges@example.org","polygon":[247,85,417,85,417,100,247,99],"spans":[{"offset":124,"length":25}]},{"content":"GSTIN : 24HDE7487RESRT4","polygon":[2,107,164,106,164,119,2,120],"spans":[{"offset":150,"length":23}]},{"content":"INVOICE # INV39980470","polygon":[239,130,378,131,378,144,239,144],"spans":[{"offset":174,"length":21}]},{"content":"Invoice Date: 12-Dec-1993","polygon":[437,128,582,128,582,140,437,141],"spans":[{"offset":196,"length":25}]},{"content":"Bill to: Amy Taylor","polygon":[0,143,104,143,104,156,0,156],"spans":[{"offset":222,"length":19}]},{"content":"18179 Davis Glen","polygon":[0,157,100,158,99,170,0,170],"spans":[{"offset":242,"length":16}]},{"content":"Kevinside, NV 48634 US","polygon":[0,172,138,171,138,184,0,185],"spans":[{"offset":259,"length":22}]},{"content":"Tel:+(726)336-1467","polygon":[0,186,107,186,108,199,0,199],"spans":[{"offset":282,"length":18}]},{"content":"Due Date : 14-Nov-2022","polygon":[438,182,574,182,574,195,438,195],"spans":[{"offset":301,"length":22}]},{"content":"Email:timothy93@example.com","polygon":[1,201,181,201,181,214,1,214],"spans":[{"offset":324,"length":27}]},{"content":"Site:https://www.martinez.com/","polygon":[1,215,179,215,179,228,1,228],"spans":[{"offset":352,"length":30}]},{"content":"SHIP_TO:","polygon":[1,240,52,241,52,253,1,252],"spans":[{"offset":383,"length":8}]},{"content":"Jordan Dickerson","polygon":[1,253,95,254,95,266,1,265],"spans":[{"offset":392,"length":16}]},{"content":"48293 Amanda Meadows","polygon":[1,267,131,267,131,279,1,279],"spans":[{"offset":409,"length":20}]},{"content":"Spencerport, MO 84516 US","polygon":[1,281,142,280,143,292,1,293],"spans":[{"offset":430,"length":24}]},{"content":"Tel:+(978)850-6997","polygon":[1,293,100,293,100,305,1,305],"spans":[{"offset":455,"length":18}]},{"content":"Email:vsmith@example.org","polygon":[1,306,146,307,146,320,1,319],"spans":[{"offset":474,"length":24}]},{"content":"Site:http://neal.com/","polygon":[1,320,107,320,107,333,1,332],"spans":[{"offset":499,"length":21}]},{"content":"ITEMS","polygon":[109,465,141,465,141,475,109,475],"spans":[{"offset":521,"length":5}]},{"content":"QUANTITY","polygon":[298,465,351,465,351,475,299,476],"spans":[{"offset":527,"length":8}]},{"content":"PRICE","polygon":[459,465,491,465,491,475,459,475],"spans":[{"offset":536,"length":5}]},{"content":"Career score point.","polygon":[82,484,168,484,168,494,82,494],"spans":[{"offset":542,"length":19}]},{"content":"6.00","polygon":[314,484,335,484,335,493,314,493],"spans":[{"offset":562,"length":4}]},{"content":"$11.15","polygon":[458,483,491,483,491,494,458,494],"spans":[{"offset":567,"length":6}]},{"content":"Can party bring.","polygon":[89,501,161,502,161,513,88,513],"spans":[{"offset":574,"length":16}]},{"content":"1.00","polygon":[314,502,335,502,335,511,314,511],"spans":[{"offset":591,"length":4}]},{"content":"$22.17","polygon":[458,501,491,501,491,511,458,512],"spans":[{"offset":596,"length":6}]},{"content":"Shoulder despite could popular.","polygon":[53,519,196,519,196,531,53,530],"spans":[{"offset":603,"length":31}]},{"content":"6.00","polygon":[314,520,335,520,335,529,314,529],"spans":[{"offset":635,"length":4}]},{"content":"$87.14","polygon":[458,519,490,519,490,529,458,529],"spans":[{"offset":640,"length":6}]},{"content":"Allow expert.","polygon":[95,538,154,538,154,548,95,548],"spans":[{"offset":647,"length":13}]},{"content":"1.00","polygon":[315,538,335,538,335,547,315,547],"spans":[{"offset":661,"length":4}]},{"content":"$86.42","polygon":[458,537,491,537,491,547,458,547],"spans":[{"offset":666,"length":6}]},{"content":"SUB_TOTAL : 698.33 $","polygon":[432,563,566,563,566,577,432,577],"spans":[{"offset":673,"length":20}]},{"content":"TOTAL : 717.43 $","polygon":[353,595,453,596,453,608,353,608],"spans":[{"offset":694,"length":16}]},{"content":"Total in words: seven hundred and seve-","polygon":[118,617,356,617,356,629,118,629],"spans":[{"offset":711,"length":39}]},{"content":"nteen point four three","polygon":[118,632,244,632,244,644,118,644],"spans":[{"offset":751,"length":22}]},{"content":"Bank Name","polygon":[2,660,68,660,68,672,2,671],"spans":[{"offset":774,"length":9}]},{"content":"Central Bank of England","polygon":[103,659,244,659,244,672,103,672],"spans":[{"offset":784,"length":23}]},{"content":"Branch Name","polygon":[2,674,80,674,80,686,2,686],"spans":[{"offset":808,"length":11}]},{"content":"Raf CAMP","polygon":[112,674,171,674,171,686,112,686],"spans":[{"offset":820,"length":8}]},{"content":"Bank Account Number 18957993","polygon":[2,688,192,688,192,700,2,701],"spans":[{"offset":829,"length":28}]},{"content":"Bank Swift Code","polygon":[2,703,97,703,97,715,2,715],"spans":[{"offset":858,"length":15}]},{"content":"SBININBB250","polygon":[115,703,195,703,195,715,115,715],"spans":[{"offset":874,"length":11}]},{"content":"Terms & Conditions","polygon":[1,742,97,742,97,753,1,752],"spans":[{"offset":886,"length":18}]},{"content":"1. Please send payment within 8 days of receiving this invoice.","polygon":[1,754,299,754,299,765,1,766],"spans":[{"offset":905,"length":63}]},{"content":"There will be a 2.5% interest charge per month on late invoices.","polygon":[1,766,302,766,302,777,1,777],"spans":[{"offset":969,"length":64}]},{"content":"2. Please include the Invoice number in your payment notes.","polygon":[1,778,288,778,288,790,1,789],"spans":[{"offset":1034,"length":59}]}],"spans":[{"offset":0,"length":1093}],"kind":"document"}],"tables":[{"rowCount":5,"columnCount":3,"cells":[{"kind":"columnHeader","rowIndex":0,"columnIndex":0,"content":"ITEMS","boundingRegions":[{"pageNumber":1,"polygon":[0,461,249,461,249,479,0,479]}],"spans":[{"offset":521,"length":5}]},{"kind":"columnHeader","rowIndex":0,"columnIndex":1,"content":"QUANTITY","boundingRegions":[{"pageNumber":1,"polygon":[249,461,398,461,398,479,249,479]}],"spans":[{"offset":527,"length":8}]},{"kind":"columnHeader","rowIndex":0,"columnIndex":2,"content":"PRICE","boundingRegions":[{"pageNumber":1,"polygon":[398,461,548,461,548,479,398,479]}],"spans":[{"offset":536,"length":5}]},{"rowIndex":1,"columnIndex":0,"content":"Career score point.","boundingRegions":[{"pageNumber":1,"polygon":[0,479,249,479,249,496,0,496]}],"spans":[{"offset":542,"length":19}]},{"rowIndex":1,"columnIndex":1,"content":"6.00","boundingRegions":[{"pageNumber":1,"polygon":[249,479,398,479,398,496,249,496]}],"spans":[{"offset":562,"length":4}]},{"rowIndex":1,"columnIndex":2,"content":"$11.15","boundingRegions":[{"pageNumber":1,"polygon":[398,479,548,479,548,496,398,496]}],"spans":[{"offset":567,"length":6}]},{"rowIndex":2,"columnIndex":0,"content":"Can party bring.","boundingRegions":[{"pageNumber":1,"polygon":[0,496,249,496,249,515,0,515]}],"spans":[{"offset":574,"length":16}]},{"rowIndex":2,"columnIndex":1,"content":"1.00","boundingRegions":[{"pageNumber":1,"polygon":[249,496,398,496,398,515,249,515]}],"spans":[{"offset":591,"length":4}]},{"rowIndex":2,"columnIndex":2,"content":"$22.17","boundingRegions":[{"pageNumber":1,"polygon":[398,496,548,496,548,515,398,515]}],"spans":[{"offset":596,"length":6}]},{"rowIndex":3,"columnIndex":0,"content":"Shoulder despite could popular.","boundingRegions":[{"pageNumber":1,"polygon":[0,515,249,515,249,532,0,532]}],"spans":[{"offset":603,"length":31}]},{"rowIndex":3,"columnIndex":1,"content":"6.00","boundingRegions":[{"pageNumber":1,"polygon":[249,515,398,515,398,532,249,532]}],"spans":[{"offset":635,"length":4}]},{"rowIndex":3,"columnIndex":2,"content":"$87.14","boundingRegions":[{"pageNumber":1,"polygon":[398,515,548,515,548,532,398,532]}],"spans":[{"offset":640,"length":6}]},{"rowIndex":4,"columnIndex":0,"content":"Allow expert.","boundingRegions":[{"pageNumber":1,"polygon":[0,532,249,532,249,550,0,550]}],"spans":[{"offset":647,"length":13}]},{"rowIndex":4,"columnIndex":1,"content":"1.00","boundingRegions":[{"pageNumber":1,"polygon":[249,532,398,532,399,550,249,550]}],"spans":[{"offset":661,"length":4}]},{"rowIndex":4,"columnIndex":2,"content":"$86.42","boundingRegions":[{"pageNumber":1,"polygon":[398,532,548,532,548,550,399,550]}],"spans":[{"offset":666,"length":6}]}],"boundingRegions":[{"pageNumber":1,"polygon":[1,460,550,460,551,552,1,552]}],"spans":[{"offset":521,"length":151}]}],"styles":[],"documents":[{"docType":"invoice","boundingRegions":[{"pageNumber":1,"polygon":[0,0,595,0,595,841,0,841]}],"fields":{"BillingAddress":{"type":"address","content":"18179 Davis Glen\nKevinside, NV 48634 US","boundingRegions":[{"pageNumber":1,"polygon":[0,157,138,157,138,185,0,185]}],"confidence":0.886,"spans":[{"offset":242,"length":39}],"valueAddress":{"houseNumber":"18179","road":"Davis Glen\nKevinside","postalCode":"48634","state":"NV","countryRegion":"US","streetAddress":"18179 Davis Glen\nKevinside"}},"BillingAddressRecipient":{"type":"string","valueString":"Amy Taylor","content":"Amy Taylor","boundingRegions":[{"pageNumber":1,"polygon":[37,143,104,143,104,156,37,156]}],"confidence":0.916,"spans":[{"offset":231,"length":10}]},"CustomerName":{"type":"string","valueString":"Amy Taylor","content":"Amy Taylor","boundingRegions":[{"pageNumber":1,"polygon":[37,143,104,143,104,156,37,156]}],"confidence":0.916,"spans":[{"offset":231,"length":10}]},"DueDate":{"type":"date","valueDate":"2022-11-14","content":"14-Nov-2022","boundingRegions":[{"pageNumber":1,"polygon":[502,182,575,182,575,195,502,195]}],"confidence":0.961,"spans":[{"offset":312,"length":11}]},"InvoiceDate":{"type":"date","valueDate":"1993-12-12","content":"12-Dec-1993","boundingRegions":[{"pageNumber":1,"polygon":[512,128,583,128,583,141,512,141]}],"confidence":0.965,"spans":[{"offset":210,"length":11}]},"InvoiceId":{"type":"string","valueString":"INV39980470","content":"INV39980470","boundingRegions":[{"pageNumber":1,"polygon":[304,131,378,131,378,144,304,144]}],"confidence":0.965,"spans":[{"offset":184,"length":11}]},"InvoiceTotal":{"type":"currency","valueCurrency":{"currencySymbol":"$","amount":717.43,"currencyCode":"USD"},"content":"717.43 $","boundingRegions":[{"pageNumber":1,"polygon":[405,596,454,596,454,608,405,608]}],"confidence":0.925,"spans":[{"offset":702,"length":8}]},"Items":{"type":"array","valueArray":[{"type":"object","valueObject":{"Amount":{"type":"currency","valueCurrency":{"currencySymbol":"$","amount":11.15,"currencyCode":"USD"},"content":"$11.15","boundingRegions":[{"pageNumber":1,"polygon":[458,483,492,483,492,494,458,494]}],"confidence":0.966,"spans":[{"offset":567,"length":6}]},"Description":{"type":"string","valueString":"Career score point.","content":"Career score point.","boundingRegions":[{"pageNumber":1,"polygon":[82,484,168,484,168,494,82,494]}],"confidence":0.95,"spans":[{"offset":542,"length":19}]},"Quantity":{"type":"number","valueNumber":6,"content":"6.00","boundingRegions":[{"pageNumber":1,"polygon":[314,484,336,484,336,493,314,493]}],"confidence":0.952,"spans":[{"offset":562,"length":4}]}},"content":"Career score point.\n6.00\n$11.15","boundingRegions":[{"pageNumber":1,"polygon":[82,483,492,483,492,494,82,494]}],"confidence":0.923,"spans":[{"offset":542,"length":31}]},{"type":"object","valueObject":{"Amount":{"type":"currency","valueCurrency":{"currencySymbol":"$","amount":22.17,"currencyCode":"USD"},"content":"$22.17","boundingRegions":[{"pageNumber":1,"polygon":[458,501,491,501,491,512,458,512]}],"confidence":0.949,"spans":[{"offset":596,"length":6}]},"Description":{"type":"string","valueString":"Can party bring.","content":"Can party bring.","boundingRegions":[{"pageNumber":1,"polygon":[88,502,161,502,161,513,88,513]}],"confidence":0.949,"spans":[{"offset":574,"length":16}]},"Quantity":{"type":"number","valueNumber":1,"content":"1.00","boundingRegions":[{"pageNumber":1,"polygon":[314,502,335,502,335,511,314,511]}],"confidence":0.952,"spans":[{"offset":591,"length":4}]}},"content":"Can party bring.\n1.00\n$22.17","boundingRegions":[{"pageNumber":1,"polygon":[88,501,491,501,491,513,88,513]}],"confidence":0.924,"spans":[{"offset":574,"length":28}]},{"type":"object","valueObject":{"Amount":{"type":"currency","valueCurrency":{"currencySymbol":"$","amount":87.14,"currencyCode":"USD"},"content":"$87.14","boundingRegions":[{"pageNumber":1,"polygon":[458,519,491,519,491,529,458,530]}],"confidence":0.944,"spans":[{"offset":640,"length":6}]},"Description":{"type":"string","valueString":"Shoulder despite could popular.","content":"Shoulder despite could popular.","boundingRegions":[{"pageNumber":1,"polygon":[53,519,196,519,196,531,53,531]}],"confidence":0.95,"spans":[{"offset":603,"length":31}]},"Quantity":{"type":"number","valueNumber":6,"content":"6.00","boundingRegions":[{"pageNumber":1,"polygon":[314,520,335,520,335,529,314,529]}],"confidence":0.952,"spans":[{"offset":635,"length":4}]}},"content":"Shoulder despite could popular.\n6.00\n$87.14","boundingRegions":[{"pageNumber":1,"polygon":[53,519,491,519,491,531,53,531]}],"confidence":0.928,"spans":[{"offset":603,"length":43}]},{"type":"object","valueObject":{"Amount":{"type":"currency","valueCurrency":{"currencySymbol":"$","amount":86.42,"currencyCode":"USD"},"content":"$86.42","boundingRegions":[{"pageNumber":1,"polygon":[458,537,491,537,491,547,458,547]}],"confidence":0.947,"spans":[{"offset":666,"length":6}]},"Description":{"type":"string","valueString":"Allow expert.","content":"Allow expert.","boundingRegions":[{"pageNumber":1,"polygon":[95,538,154,538,154,548,95,548]}],"confidence":0.951,"spans":[{"offset":647,"length":13}]},"Quantity":{"type":"number","valueNumber":1,"content":"1.00","boundingRegions":[{"pageNumber":1,"polygon":[315,538,335,538,335,547,315,547]}],"confidence":0.951,"spans":[{"offset":661,"length":4}]}},"content":"Allow expert.\n1.00\n$86.42","boundingRegions":[{"pageNumber":1,"polygon":[95,537,491,537,491,548,95,548]}],"confidence":0.916,"spans":[{"offset":647,"length":25}]}]},"PaymentDetails":{"type":"array","valueArray":[{"type":"object","valueObject":{"SWIFT":{"type":"string","valueString":"SBININBB250","content":"SBININBB250","boundingRegions":[{"pageNumber":1,"polygon":[115,703,196,703,196,715,115,715]}],"confidence":0.771,"spans":[{"offset":874,"length":11}]}},"confidence":0.995}]},"ShippingAddress":{"type":"address","content":"48293 Amanda Meadows\nSpencerport, MO 84516 US","boundingRegions":[{"pageNumber":1,"polygon":[1,267,143,267,143,293,1,293]}],"confidence":0.887,"spans":[{"offset":409,"length":45}],"valueAddress":{"houseNumber":"48293","road":"Amanda Meadows","postalCode":"84516","city":"Spencerport","state":"MO","countryRegion":"US","streetAddress":"48293 Amanda Meadows"}},"ShippingAddressRecipient":{"type":"string","valueString":"Jordan Dickerson","content":"Jordan Dickerson","boundingRegions":[{"pageNumber":1,"polygon":[1,253,95,254,95,267,1,265]}],"confidence":0.712,"spans":[{"offset":392,"length":16}]},"SubTotal":{"type":"currency","valueCurrency":{"currencySymbol":"$","amount":698.33,"currencyCode":"USD"},"content":"698.33 $","boundingRegions":[{"pageNumber":1,"polygon":[515,563,567,563,567,577,515,577]}],"confidence":0.938,"spans":[{"offset":685,"length":8}]},"VendorAddress":{"type":"address","content":"Address:8110 Lee Haven\nWest Michele, IN 23979 US","boundingRegions":[{"pageNumber":1,"polygon":[3,50,157,50,157,77,3,77]}],"confidence":0.887,"spans":[{"offset":27,"length":22},{"offset":57,"length":25}],"valueAddress":{"houseNumber":"8110","road":"Lee Haven\nWest","postalCode":"23979","city":"Michele","state":"IN","countryRegion":"US","streetAddress":"8110 Lee Haven\nWest","house":"Address"}},"VendorAddressRecipient":{"type":"string","valueString":"Graham, Carrillo and Stark","content":"Graham, Carrillo and Stark","boundingRegions":[{"pageNumber":1,"polygon":[2,20,157,20,157,34,2,34]}],"confidence":0.927,"spans":[{"offset":0,"length":26}]},"VendorName":{"type":"string","valueString":"Graham, Carrillo and Stark","content":"Graham, Carrillo and Stark","boundingRegions":[{"pageNumber":1,"polygon":[2,20,157,20,157,34,2,34]}],"confidence":0.927,"spans":[{"offset":0,"length":26}]},"VendorTaxId":{"type":"string","valueString":"24HDE7487RESRT4","content":"24HDE7487RESRT4","boundingRegions":[{"pageNumber":1,"polygon":[50,107,165,107,165,119,50,120]}],"confidence":0.631,"spans":[{"offset":158,"length":15}]}},"confidence":1,"spans":[{"offset":0,"length":1093}]}],"contentFormat":"text"}}